aes_cipher/__init__.py
aes_cipher/_version.py
aes_cipher/aes_cbc_decrypter.py
aes_cipher/aes_cbc_encrypter.py
aes_cipher/aes_const.py
aes_cipher/data_decrypter.py
aes_cipher/data_encrypter.py
aes_cipher/data_ex.py
aes_cipher/file_decrypter.py
aes_cipher/file_encrypter.py
aes_cipher/file_reader.py
aes_cipher/file_writer.py
aes_cipher/hmac_sha256.py
aes_cipher/ikey_derivator.py
aes_cipher/key_iv_generator.py
aes_cipher/loggable_base.py
aes_cipher/logger.py
aes_cipher/pbkdf2_sha512.py
aes_cipher/salt_length.py
aes_cipher/scrypt.py
aes_cipher/utils.py
aes_cipher-2.0.1.dist-info/LICENSE
aes_cipher-2.0.1.dist-info/METADATA
aes_cipher-2.0.1.dist-info/WHEEL
aes_cipher-2.0.1.dist-info/top_level.txt
aes_cipher-2.0.1.dist-info/RECORD
