Metadata-Version: 2.1
Name: aes_cipher
Version: 2.0.1
Summary: Cipher based on AES256-CBC
Home-page: https://github.com/ebellocchia/aes_cipher
Download-URL: https://github.com/ebellocchia/aes_cipher/archive/v2.0.1.tar.gz
Author: Emanuele Bellocchia
Author-email: ebellocchia@gmail.com
Maintainer: Emanuele Bellocchia
Maintainer-email: ebellocchia@gmail.com
License: MIT
Keywords: cipher,aes,aes256,sha,sha256,sha512,pbkdf2,pbkdf2-sha512,hmac,hmac-sha256
Platform: any
Classifier: Programming Language :: Python :: 3.7
Classifier: Programming Language :: Python :: 3.8
Classifier: Programming Language :: Python :: 3.9
Classifier: Programming Language :: Python :: 3.10
Classifier: Programming Language :: Python :: 3.11
Classifier: Programming Language :: Python :: 3.12
Classifier: Development Status :: 5 - Production/Stable
Classifier: License :: OSI Approved :: MIT License
Classifier: Operating System :: OS Independent
Classifier: Intended Audience :: Developers
Requires-Python: >=3.7
License-File: LICENSE
Requires-Dist: pycryptodome ~=3.1
